mytool4docker/__init__.py
mytool4docker/uninstall.py
mytool4docker-0.0.1.dist-info/LICENSE
mytool4docker-0.0.1.dist-info/METADATA
mytool4docker-0.0.1.dist-info/WHEEL
mytool4docker-0.0.1.dist-info/top_level.txt
mytool4docker-0.0.1.dist-info/RECORD
