Metadata-Version: 2.1
Name: mytool4docker
Version: 0.0.1
Summary: mytool4docker = mytoolset + akatool
Home-page: https://github.com/FarAway6834/mytool4docker
Author: du7ec
Author-email: dutec6834@gmail.com
Keywords: mytool4docker,=,mytoolset,+,akatool
Classifier: Programming Language :: Python :: 3.4
Classifier: Programming Language :: Python :: 3.5
Classifier: Programming Language :: Python :: 3.6
Classifier: Programming Language :: Python :: 3.7
Classifier: Programming Language :: Python :: 3.8
Classifier: Programming Language :: Python :: 3.9
Classifier: Programming Language :: Python :: 3.10
Classifier: Programming Language :: Python :: 3.11
Classifier: Programming Language :: Python :: 3.12
Classifier: Programming Language :: Python :: 3.13
Classifier: Programming Language :: Python :: 3.14
Requires-Python: >=3.4
License-File: LICENSE
Requires-Dist: akatool
Requires-Dist: mytoolset
